docpixie/__init__.py
docpixie/cli.py
docpixie/docpixie.py
docpixie/exceptions.py
docpixie/py.typed
docpixie/ai/__init__.py
docpixie/ai/agent.py
docpixie/ai/context_processor.py
docpixie/ai/page_selector.py
docpixie/ai/prompts.py
docpixie/ai/query_classifier.py
docpixie/ai/query_reformulator.py
docpixie/ai/summarizer.py
docpixie/ai/synthesizer.py
docpixie/ai/task_planner.py
docpixie/cli/__init__.py
docpixie/cli/app.py
docpixie/cli/commands.py
docpixie/cli/config.py
docpixie/cli/conversation_storage.py
docpixie/cli/docpixie_manager.py
docpixie/cli/event_handlers.py
docpixie/cli/legacy.py
docpixie/cli/state_manager.py
docpixie/cli/styles.py
docpixie/cli/task_display.py
docpixie/cli/widgets/__init__.py
docpixie/cli/widgets/chat_area.py
docpixie/cli/widgets/command_palette.py
docpixie/cli/widgets/conversation_manager.py
docpixie/cli/widgets/document_manager.py
docpixie/cli/widgets/model_selector.py
docpixie/core/__init__.py
docpixie/core/config.py
docpixie/core/utils.py
docpixie/models/__init__.py
docpixie/models/agent.py
docpixie/models/document.py
docpixie/processors/__init__.py
docpixie/processors/base.py
docpixie/processors/factory.py
docpixie/processors/image.py
docpixie/processors/pdf.py
docpixie/providers/__init__.py
docpixie/providers/anthropic.py
docpixie/providers/base.py
docpixie/providers/factory.py
docpixie/providers/openai.py
docpixie/providers/openrouter.py
docpixie/storage/__init__.py
docpixie/storage/base.py
docpixie/storage/local.py
docpixie/storage/memory.py
docpixie/utils/__init__.py
docpixie/utils/async_helpers.py
docpixie-0.1.0.dist-info/licenses/LICENSE
docpixie-0.1.0.dist-info/METADATA
docpixie-0.1.0.dist-info/WHEEL
docpixie-0.1.0.dist-info/entry_points.txt
docpixie-0.1.0.dist-info/top_level.txt
docpixie-0.1.0.dist-info/RECORD
