Metadata-Version: 2.4
Name: docpixie
Version: 0.1.0
Summary: A lightweight, vision-based document question-answering system
Author: DocPixie Team
Maintainer: DocPixie Team
License-Expression: MIT
Project-URL: Homepage, https://github.com/qnguyen3/docpixie
Project-URL: Documentation, https://github.com/qnguyen3/docpixie#readme
Project-URL: Repository, https://github.com/qnguyen3/docpixie.git
Project-URL: Issues, https://github.com/qnguyen3/docpixie/issues
Classifier: Development Status :: 3 - Alpha
Classifier: Intended Audience :: Developers
Classifier: Programming Language :: Python :: 3
Classifier: Programming Language :: Python :: 3.8
Classifier: Programming Language :: Python :: 3.9
Classifier: Programming Language :: Python :: 3.10
Classifier: Programming Language :: Python :: 3.11
Classifier: Programming Language :: Python :: 3.12
Classifier: Topic :: Software Development :: Libraries :: Python Modules
Classifier: Topic :: Scientific/Engineering :: Artificial Intelligence
Requires-Python: >=3.8
License-File: LICENSE
Requires-Dist: Pillow>=10.0.0
Requires-Dist: PyMuPDF>=1.23.0
Requires-Dist: openai>=1.0.0
Requires-Dist: anthropic>=0.10.0
Requires-Dist: textual>=0.47.0
Requires-Dist: textual-dev>=1.3.0
Requires-Dist: pyfiglet>=0.8.0
Provides-Extra: dev
Requires-Dist: pytest>=7.0.0; extra == "dev"
Requires-Dist: pytest-asyncio>=0.21.0; extra == "dev"
Requires-Dist: build>=1.0.0; extra == "dev"
Requires-Dist: twine>=4.0.0; extra == "dev"
Dynamic: license-file
